pygpp/__init__.py
pygpp/gpp.py
pygpp-0.0.1.dist-info/licenses/LICENSE
pygpp-0.0.1.dist-info/WHEEL
pygpp-0.0.1.dist-info/METADATA
pygpp-0.0.1.dist-info/RECORD
