Metadata-Version: 2.4
Name: pygpp
Version: 0.0.1
Summary: A Python abstraction layer for GW-Instek GPP power supplies
Keywords: gwinstek,gpp,power supply,scpi,visa
Author: Sam Shahrokni
Author-email: Sam Shahrokni <sam@shahrokni.nl>
License-Expression: MIT
License-File: LICENSE
Classifier: Programming Language :: Python :: 3
Classifier: Operating System :: OS Independent
Requires-Dist: pyvisa>=1.16
Requires-Dist: ruff ; extra == 'dev'
Requires-Dist: mypy ; extra == 'dev'
Requires-Dist: pre-commit ; extra == 'dev'
Requires-Dist: coverage ; extra == 'dev'
Requires-Dist: vulture ; extra == 'dev'
Requires-Dist: pandas ; extra == 'examples'
Requires-Dist: matplotlib ; extra == 'examples'
Requires-Dist: rich ; extra == 'examples'
Requires-Dist: numpy ; extra == 'examples'
Requires-Python: >=3.12
Project-URL: Homepage, https://gitlab.com/samshahrokni/pyGPP
Provides-Extra: dev
Provides-Extra: examples
